lincolntools
