Metadata-Version: 2.1
Name: lincolntools-config
Version: 1.0.5
Summary: Boîte à outils Python made in Lincoln
Home-page: https://github.com/Lincoln-France/lincolntools-config
Author: Lincoln Innovation
Author-email: labinnovation@mel.lincoln.fr
License: UNKNOWN
Download-URL: https://github.com/Lincoln-France/lincolntools-config/archive/refs/tags/v1.0.5.tar.gz
Keywords: configuration,yaml,lincoln,lincolntools,lincolntools-config
Platform: UNKNOWN
Classifier: Development Status :: 5 - Production/Stable
Classifier: Intended Audience :: Developers
Classifier: Natural Language :: English
Classifier: Programming Language :: Python :: 3
Classifier: Programming Language :: Python :: 3.5
Classifier: Programming Language :: Python :: 3.6
Classifier: Programming Language :: Python :: 3.7
Classifier: Programming Language :: Python :: 3.8
Requires-Python: >=3.5
License-File: LICENSE.md
License-File: AUTHORS.md
